Workbook

Sheet Comparison
Y2: part utilization | Z2: part utilization
C3: Date | D3: account | E3: custacct | F3: xchgmkt | G3: card id | H3: client_name | I3: team name | J3: mktname | K3: flag บุคคลธรรมดา/นิติบุคคล | L3: flag lombard loan | M3: flag property backed loan (PPBL) | N3: flag TFSC | O3: flag algo trade | P3: flag cashcredit | Q3: open date | R3: Last trade | S3: Last date of temporary credit line reduction | T3: Last date change credit line (วงเงินถาวร) | U3: Credit line (วงเงินถาวร) | V3: มูลค่าหุ้นหลัง Haircut + เงินสด as of date | W3: Max (มูลค่าหุ้นหลัง Haircut + เงินสด) since last year | X3: Loan (credit balance) | Y3: max (ar_trade/comp_creditline) since last year | Z3: max(debt/comp_creditline) since last year
B4: สำหรับบัญชี หุ้น | C4: as of date | D4: เลขที่บัญชี | E4: เลขที่ลูกค้า | F4: เลขที่ตลาดซื้อขาย (1) | G4: เลขประจำตัวผู้เสียภาษี | H4: ชื่อลูกค้า | I4: ชื่อทีมที่ดูแลลูกค้า | J4: ชื่อ AO ที่ดูแลลูกค้า | K4: บุคคลธรรมดา or นิติบุคคล | L4: Yes or No | M4: Yes or No | N4: Yes or No | O4: Yes or No | Q4: วันที่เปิดบัญชี | R4: วันที่มีการซื้อขายล่าสุด | S4: วันล่าสุดที่มีการปรับลด วงเงินแบบชั่วคราว | T4: วันที่ล่าสุดที่มีการปรับ วงเงินแบบถาวร | U4: ข้อมูลวงเงินแบบถาวร ของลูกค้า | V4: มูลค่าหุ้นหลัง Haircut + เงินสด ของ as of date | W4: นำมูลค่าหุ้นหลัง Haircut + เงินสด ในแต่ละวัน มาหาค่าที่สูงสุดของแต่ละบัญชี | X4: มูลหนี้ของลูกค้า กรณีเป็นบัญชี Credit balance | Y4: %utilization ของวงเงิน ที่คิดจากการนำ AR_trade/comp_creditline ของแต่ละวันมาหาค่าที่สูงสุด | Z4: %utilization ของวงเงิน ที่คิดจากการนำ debt/comp_creditline ของแต่ละวันมาหาค่าที่สูงสุด
B5: สำหรับบัญชี Bond | C5: Y | D5: Y | E5: Y | F5: Y(เลขที่ตลาดซื้อขาย 3) | G5: Y | H5: Y | I5: Y | J5: Y | K5: Y | L5: Y | M5: Y | N5: N | O5: N | P5: N | Q5: Y | R5: Y | S5: N | T5: Y | U5: Y | V5: "- มูลค่า Bond (bond mktval) - มูลค่า Bond mktval ของ as of date as of date | W5: มูลค่า Bond (bond mktval) as of date - นำมูลค่า Bond mktval ในแต่ละวัน มาหาค่าที่สูงสุดของแต่ละบัญชี | X5: N | Y5: max (ar_trade/comp_creditline) since last year %utilization ของวงเงิน ที่คิดจากการนำ AR_trade/comp_creditline ของแต่ละวันมาหาค่าที่สูงสุด | Z5: N
B6: สำหรับบัญชี SBL | C6: Y | D6: Y | E6: Y | F6: Y | G6: Y | H6: Y | I6: Y | J6: Y | K6: Y | L6: Y | M6: Y | N6: Y | O6: Y | P6: flag cashcredit | Q6: Y | R6: Y | S6: N | T6: Y | U6: Y | V6: Y | W6: Y | X6: Y | Y6: Y | Z6: Y
B7: สำหรับบัญชี Off-shore | C7: Y | D7: Y | E7: N | F7: N | G7: Y | H7: Y | I7: Y | J7: Y | K7: Y | L7: Y | M7: Y | N7: N | O7: N | P7: N | Q7: Y | R7: Y | S7: N | T7: Y | U7: Y | V7: THB Eqv. Amount as of date มูลค่า Asset ของลูกค้า สกุลเงินบาท รวมทุก product | W7: Max (THB Eqv. Amount ) since last year นำมูลค่า Asset ของลูกค้า สกุลเงินบาท รวมทุก product ในแต่ละวัน มาหาค่าที่สูงสุดของแต่ละบัญชี | X7: N | Y7: Max (มูลค่าซื้อ product ต่างๆ/credit line) since last year %utilization ของวงเงิน ที่คิดจากการนำ มูลค่าซื้อของทุก product / comp_creditline ของแต่ละวันมาหาค่าที่สูงสุด | Z7: N
C8: มี | D8: มี | G8: มี CDB | H8: มี CDB | I8: มี CDB | J8: มี CDB | K8: มี CDB | L8: ยังไม่มี กำลัง explore | M8: ยังไม่มี กำลัง explore | Q8: มี CDB | R8: มี CDB | T8: มี SBA ปัจจุบันไม่มีข้อมูลใน CDB | U8: มี CDB | V8: มี CDB | W8: มี CDB | Y8: มี CDB
B9: สำหรับบัญชี TFEX | C9: Y | D9: Y | E9: N | F9: N | G9: Y | H9: Y | I9: Y | J9: Y | K9: Y | L9: Y | M9: Y | N9: N | O9: N | P9: N | Q9: Y | R9: Y | S9: N | T9: *Y | U9: Y | V9: initial margin (initial margin ของบัญชี) as of date | W9: Max (initial margin) since last year (นำ initial margin ของบัญชี ในแต่ละวัน มาหาค่าที่สูงสุดของแต่ละบัญชี) | X9: equity balance(equity balance ของบัญชี) as of date | Y9: Max (equity balance) since last year (นำ equity balance ของบัญชี ในแต่ละวัน มาหาค่าที่สูงสุดของแต่ละบัญชี) | Z9: Max (initial margin/credit line) since last year (%utilization ของวงเงิน ที่คิดจากการนำ initial margin/comp_creditline ของแต่ละวันมาหาค่าที่สูงสุด)
C10: มี | D10: มี | G10: มี CDB | H10: มี CDB | I10: มี CDB | J10: มี CDB | K10: มี CDB | L10: ไม่แน่ใจว่าเมื่อก่อนมีไหม | M10: ไม่แน่ใจว่าเมื่อก่อนมีไหม | Q10: มี CDB | R10: มี CDB | T10: E-service ปัจจุบันไม่มีข้อมูลใน CDB | U10: E-service | V10: มี CDB | W10: มี CDB | X10: มี CDB | Y10: มี CDB | Z10: มี CDB

Sheet data
B3: ขอข้อมูลเฉพาะบัญชีที่ยังไม่ปิดบัญชี | F3: ส่งให้พี่ oper อนุมัติ | U3: บัญชี bond ไม่มีเงินสด | W3: มูลค่าหุ้นหลัง haircut เข้า datalake เพิ่ม
B4: ขอข้อมูลเฉพาะบัญชีที่เปิดบัญชีมาเกิน 1 ปี | F4: data request
A6: SBA
O7: แยก credit balance ออกมาได้
D8: custacct 6 แยกได้เพิ่ม เป็น credit balance | H8: ข้อมูลสามารถแยกทีม Ebiz ออกมาได้ไหม | L8: Tlock | N8: algo trading internet flag = 3 and usefront = H | O8: 6 cash account A cash balance 0 สถาบันเทรดตามวงเงิน | R8: วันล่าสุดที่มีการปรับลดวงเงินชั่วคราว ใช้สำหรับแยกบัญชี Structure note | V8: เงินสดมีเก็บแค่ 2 week - 1 เดือน ใน SBA
A9: สำหรับบัญชี หุ้น | X9: part utilization | Y9: part utilization
B10: Date | C10: account | D10: custacct | E10: xchgmkt | F10: card id | G10: client_name | H10: team name | I10: mktname | J10: flag บุคคลธรรมดา/นิติบุคคล | K10: flag lombard loan | L10: flag property backed loan (PPBL) | M10: flag TFSC | N10: flag algo trade | O10: flag cashcredit | P10: open date | Q10: Last trade | R10: Last date of temporary credit line reduction | S10: Last date change credit line (วงเงินถาวร) | T10: Credit line (วงเงินถาวร) | U10: มูลค่าหุ้นหลัง Haircut + เงินสด as of date | V10: Max (มูลค่าหุ้นหลัง Haircut + เงินสด) since last year | W10: Loan (credit balance) | X10: max (ar_trade/comp_creditline) since last year | Y10: max(debt/comp_creditline) since last year
A11: Definition | B11: as of date | C11: เลขที่บัญชี | D11: เลขที่ลูกค้า | E11: เลขที่ตลาดซื้อขาย (1) | F11: เลขประจำตัวผู้เสียภาษี | G11: ชื่อลูกค้า | H11: ชื่อทีมที่ดูแลลูกค้า | I11: ชื่อ AO ที่ดูแลลูกค้า | J11: บุคคลธรรมดา or นิติบุคคล | K11: Yes or No | L11: Yes or No | M11: Yes or No | N11: Yes or No | P11: วันที่เปิดบัญชี | Q11: วันที่มีการซื้อขายล่าสุด | R11: วันล่าสุดที่มีการปรับลด วงเงินแบบชั่วคราว | S11: วันที่ล่าสุดที่มีการปรับ วงเงินแบบถาวร | T11: ข้อมูลวงเงินแบบถาวร ของลูกค้า | U11: มูลค่าหุ้นหลัง Haircut + เงินสด ของ as of date | V11: นำมูลค่าหุ้นหลัง Haircut + เงินสด ในแต่ละวัน มาหาค่าที่สูงสุดของแต่ละบัญชี | W11: มูลหนี้ของลูกค้า กรณีเป็นบัญชี Credit balance | X11: %utilization ของวงเงิน ที่คิดจากการนำ AR_trade/comp_creditline ของแต่ละวันมาหาค่าที่สูงสุด | Y11: %utilization ของวงเงิน ที่คิดจากการนำ debt/comp_creditline ของแต่ละวันมาหาค่าที่สูงสุด
A12: มี/ไม่มีข้อมูล | B12: มี | C12: มี | D12: มี | E12: มี | F12: มี | G12: มี | H12: มี | I12: มี | J12: มี | K12: มี | L12: มี | M12: มี | N12: มี | O12: มี | P12: มี | Q12: มี | R12: มี | S12: มี | T12: มี | U12: มี | V12: มี | W12: มี
A14: สำหรับบัญชี Bond
B15: Date | C15: account | D15: custacct | E15: xchgmkt | F15: card id | G15: client_name | H15: team name | I15: mktname | J15: flag บุคคลธรรมดา/นิติบุคคล | K15: flag lombard loan | L15: flag property backed loan (PPBL) | P15: open date | Q15: Last trade | S15: Last date change credit line (วงเงินถาวร) | T15: Credit line (วงเงินถาวร) | U15: มูลค่า Bond (bond mktval) as of date | V15: มูลค่า Bond (bond mktval) as of date | X15: max (ar_trade/comp_creditline) since last year
A16: Definition | B16: as of date | C16: เลขที่บัญชี | D16: เลขที่ลูกค้า | E16: เลขที่ตลาดซื้อขาย (3) | F16: เลขประจำตัวผู้เสียภาษี | G16: ชื่อลูกค้า | H16: ชื่อทีมที่ดูแลลูกค้า | I16: ชื่อ AO ที่ดูแลลูกค้า | J16: บุคคลธรรมดา or นิติบุคคล | K16: Yes or No | L16: Yes or No | P16: วันที่เปิดบัญชี | Q16: วันที่มีการซื้อขายล่าสุด | S16: วันที่ล่าสุดที่มีการปรับ วงเงินแบบถาวร | T16: ข้อมูลวงเงินแบบถาวร ของลูกค้า | U16: มูลค่า Bond mktval ของ as of date | V16: นำมูลค่า Bond mktval ในแต่ละวัน มาหาค่าที่สูงสุดของแต่ละบัญชี | X16: %utilization ของวงเงิน ที่คิดจากการนำ AR_trade/comp_creditline ของแต่ละวันมาหาค่าที่สูงสุด
A17: มี/ไม่มีข้อมูล | B17: มี | C17: มี | D17: มี | E17: มี | F17: มี | G17: มี | H17: มี | I17: มี | J17: มี | K17: มี | L17: มี | P17: มี | Q17: มี | S17: มี | T17: มี | U17: มี | V17: มีย้อนหลังไม่นาน 2week - 1 เดือน
A19: สำหรับบัญชี SBL | T19: ปรับให้เป็น 0
B20: Date | C20: account | D20: custacct | E20: xchgmkt | F20: card id | G20: client_name | H20: team name | I20: mktname | J20: flag บุคคลธรรมดา/นิติบุคคล | K20: flag lombard loan | L20: flag property backed loan (PPBL) | M20: flag TFSC | N20: flag algo trade | O20: flag cashcredit | P20: open date | Q20: Last trade | S20: Last date change credit line (วงเงินถาวร) | T20: Credit line (วงเงินถาวร) | U20: มูลค่าหุ้นหลัง Haircut + เงินสด as of date | V20: Max (มูลค่าหุ้นหลัง Haircut + เงินสด) since last year | W20: Loan (credit balance) | X20: max (ar_trade/comp_creditline) since last year | Y20: max(debt/comp_creditline) since last year
A21: Definition | B21: as of date | C21: เลขที่บัญชี | D21: เลขที่ลูกค้า | E21: เลขที่ตลาดซื้อขาย (1) | F21: เลขประจำตัวผู้เสียภาษี | G21: ชื่อลูกค้า | H21: ชื่อทีมที่ดูแลลูกค้า | I21: ชื่อ AO ที่ดูแลลูกค้า | J21: บุคคลธรรมดา or นิติบุคคล | K21: Yes or No | L21: Yes or No | M21: Yes or No | N21: Yes or No | P21: วันที่เปิดบัญชี | Q21: วันที่มีการซื้อขายล่าสุด | S21: วันที่ล่าสุดที่มีการปรับ วงเงินแบบถาวร | T21: ข้อมูลวงเงินแบบถาวร ของลูกค้า | U21: มูลค่าหุ้นหลัง Haircut + เงินสด ของ as of date | V21: นำมูลค่าหุ้นหลัง Haircut + เงินสด ในแต่ละวัน มาหาค่าที่สูงสุดของแต่ละบัญชี | W21: มูลหนี้ของลูกค้า กรณีเป็นบัญชี Credit balance | X21: %utilization ของวงเงิน ที่คิดจากการนำ AR_trade/comp_creditline ของแต่ละวันมาหาค่าที่สูงสุด | Y21: %utilization ของวงเงิน ที่คิดจากการนำ debt/comp_creditline ของแต่ละวันมาหาค่าที่สูงสุด
A22: มี/ไม่มีข้อมูล | B22: มี | C22: มี | D22: มี | E22: มี | F22: มี | G22: มี | H22: มี | I22: มี | J22: มี | K22: มี | L22: มี | M22: มี | N22: check บัญชี SBL มี algo ไหม | O22: check | P22: มี | Q22: มี | S22: มี | T22: มี | U22: มี | V22: มี | W22: มี
A24: CDB
A26: สำหรับบัญชี Off-shore | Q26: ข้อมูลทุก product | U26: ข้อมูลทุก product | W26: part utilization
B27: Date | C27: account | F27: card id | G27: client_name | H27: team name | I27: mktname | J27: flag บุคคลธรรมดา/นิติบุคคล | K27: flag lombard loan | L27: flag property backed loan (PPBL) | P27: open date | Q27: Last trade | S27: Last date change credit line (วงเงินถาวร) | T27: Credit line (วงเงินถาวร) | U27: THB Eqv. Amount as of date | V27: Max (THB Eqv. Amount ) since last year | W27: Max (มูลค่าซื้อ product ต่างๆ/credit line) since last year
A28: Definition | B28: as of date | C28: เลขที่บัญชี | F28: เลขประจำตัวผู้เสียภาษี | G28: ชื่อลูกค้า | H28: ชื่อทีมที่ดูแลลูกค้า | I28: ชื่อ AO ที่ดูแลลูกค้า | J28: บุคคลธรรมดา or นิติบุคคล | K28: Yes or No | L28: Yes or No | P28: วันที่เปิดบัญชี | Q28: วันที่มีการซื้อขายล่าสุด | S28: วันที่ล่าสุดที่มีการปรับ วงเงินแบบถาวร | T28: ข้อมูลวงเงินแบบถาวร ของลูกค้า | U28: มูลค่า Asset ของลูกค้า สกุลเงินบาท รวมทุก product | V28: นำมูลค่า Asset ของลูกค้า สกุลเงินบาท รวมทุก product ในแต่ละวัน มาหาค่าที่สูงสุดของแต่ละบัญชี | W28: %utilization ของวงเงิน ที่คิดจากการนำ มูลค่าซื้อของทุก product / comp_creditline ของแต่ละวันมาหาค่าที่สูงสุด
A29: มี/ไม่มีข้อมูล | B29: มี | C29: มี | F29: มี CDB | G29: มี CDB | H29: มี CDB | I29: มี CDB | J29: มี CDB | K29: ยังไม่มี กำลัง explore | L29: ยังไม่มี กำลัง explore | P29: มี CDB | Q29: มี CDB | S29: มี SBA ปัจจุบันไม่มีข้อมูลใน CDB | T29: มี CDB | U29: มี CDB | V29: มี CDB | W29: มี CDB
L30: บัญชีนี้ สามารถมี flag นี้ได้CQ ไม่มีข้อมูล | S30: มี temp credit แต่น้อย | T30: ต้องใช้ ใช้ข้อมูลจาก table jcas
A31: สำหรับบัญชี TFEX | Y31: part utilization
B32: Date | C32: account | F32: card id | G32: client_name | H32: team name | I32: mktname | J32: flag บุคคลธรรมดา/นิติบุคคล | K32: flag lombard loan | L32: flag property backed loan (PPBL) | P32: open date | Q32: Last trade | S32: Last date change credit line (วงเงินถาวร) | T32: Credit line (วงเงินถาวร) | U32: initial margin as of date | V32: Max (initial margin) since last year | W32: equity balance as of date | X32: Max (equity balance) since last year | Y32: Max (initial margin/credit line) since last year
A33: Definition | B33: as of date | C33: เลขที่บัญชี | F33: เลขประจำตัวผู้เสียภาษี | G33: ชื่อลูกค้า | H33: ชื่อทีมที่ดูแลลูกค้า | I33: ชื่อ AO ที่ดูแลลูกค้า | J33: บุคคลธรรมดา or นิติบุคคล | K33: Yes or No | L33: Yes or No | P33: วันที่เปิดบัญชี | Q33: วันที่มีการซื้อขายล่าสุด | S33: วันที่ล่าสุดที่มีการปรับ วงเงินแบบถาวร | T33: ข้อมูลวงเงินแบบถาวร ของลูกค้า | U33: initial margin ของบัญชี | V33: นำ initial margin ของบัญชี ในแต่ละวัน มาหาค่าที่สูงสุดของแต่ละบัญชี | W33: equity balance ของบัญชี | X33: นำ equity balance ของบัญชี ในแต่ละวัน มาหาค่าที่สูงสุดของแต่ละบัญชี | Y33: %utilization ของวงเงิน ที่คิดจากการนำ initial margin/comp_creditline ของแต่ละวันมาหาค่าที่สูงสุด
A34: มี/ไม่มีข้อมูล | B34: มี | C34: มี | F34: มี CDB | G34: มี CDB | H34: มี CDB | I34: มี CDB | J34: มี CDB | K34: ไม่แน่ใจว่าเมื่อก่อนมีไหม | L34: ไม่แน่ใจว่าเมื่อก่อนมีไหม | P34: มี CDB | Q34: มี CDB | S34: E-service ปัจจุบันไม่มีข้อมูลใน CDB | T34: E-service | U34: มี CDB | V34: มี CDB | W34: มี CDB | X34: มี CDB | Y34: มี CDB
K35: สอบถามพี่วีเพิ่ม | T35: ต้องใช้ ดึงจาก tfex client account
T36: อ้างอิงที่ eservice ไปใช้ | W36: e-service ไม่มีอัพเดทวงเงินเยอะๆ มีอัพโหลดเป็นไฟล์
S37: TFEX สามารถปรับวงเงินชั่วคราวได้ แต่จาก eservice เป็นถาวร
B40: บัญชี off-shore กับ TFEX ต้องส่งข้อมูลขอที่ไหน
B41: ปรึกษาเรื่อง utilization
B45: ตอนที่จะใส่ข้อมูลในระบบ จะต้องมีการขอข้อมูลอีกรอบ เพื่อเช็คว่าลูกค้ายังไม่ได้มีการปรับวงเงิน หรือว่าซื้อขายเพิ่ม
B47: Date | C47: account | E47: xchgmkt | F47: Last trade | G47: Last change app credit line (วงเงินถาวร)
B49: มี | C49: มี | E49: มี | F49: มี | G49: มี

Sheet equity_report
C1: datalake
A2: สำหรับบัญชี หุ้น | B2: Definition | C2: source system | D2: source table | E2: source column | F2: Formular | G2: Remark | H2: Mapping status
A3: Date | B3: as of date ของข้อมูลที่ดึงมา | C3: x | H3: Not started
A4: account | B4: เลขที่บัญชี | H4: Not started
A5: custacct | B5: เลขที่ลูกค้า | H5: Not started
A6: xchgmkt | B6: เลขที่ตลาดซื้อขาย : เป็นเลข 1 บัญชีหุ้น | H6: Not started
A7: card id | B7: เลขประจำตัวประชาชน / เลขทะเบียนนิติบุคคล | H7: Not started
A8: client_name | B8: ชื่อลูกค้า | H8: Not started
A9: team name | B9: ชื่อทีม ที่ดูแลลูกค้า | H9: Not started
A10: mktname | B10: ชื่อ AO ที่ดูแลลูกค้า | H10: Not started
A11: flag บุคคลธรรมดา/นิติบุคคล | B11: บุคคลธรรมดา or นิติบุคคล | H11: Not started
A12: flag lombard loan | B12: Yes or No | H12: Not started
A13: flag property backed loan (PPBL) | B13: Yes or No | H13: Not started
A14: flag TFSC | B14: Yes or No | H14: Not started
A15: flag algo trade | B15: Yes or No | H15: Not started
A16: flag cashcredit | H16: Not started
A17: Open date | B17: วันที่เปิดบัญชี | H17: Not started
A18: Last trade | B18: วันที่มีการซื้อขายล่าสุด | H18: Not started
A19: Last date of temporary credit line reduction | B19: วันที่ล่าสุดที่มีการปรับลด วงเงินแบบชั่วคราว | H19: Not started
A20: Last date change credit line | B20: วันที่ล่าสุดที่มีการปรับ วงเงินแบบถาวร | H20: Not started
A21: Credit line | B21: ข้อมูลวงเงินแบบถาวร ของบัญชี | H21: Not started
A22: Current asset | B22: มูลค่าหุ้นหลัง Haircut + เงินสด ของ as of date | H22: Not started
A23: Max_asset_1Year | B23: มูลค่าหุ้นหลัง Haircut + เงินสด ในแต่ละวันย้อนหลัง 1 ปี มาหาค่าที่สูงสุดของแต่ละบัญชี | H23: Not started
A24: Loan (credit balance) | B24: มูลหนี้ของลูกค้า กรณีเป็นบัญชี Credit balance | H24: Not started
A25: trade utilization% | B25: %utilization ของวงเงิน ที่คิดจากการนำ AR_trade/comp_creditline ของแต่ละวันย้อนหลัง 1 ปี มาหาค่าที่สูงสุด | F25: max of daily trade utilization daily trade utilization = AR_trade/comp_creditline | H25: Not started
A26: loan utilization% | B26: %utilization ของวงเงิน ที่คิดจากการนำ debt/comp_creditline ของแต่ละวันย้อนหลัง 1 ปี มาหาค่าที่สูงสุด | F26: max of daily loan utilization daily loan utilization = AR_trade/comp_creditline | H26: Not started

Sheet bond_report
C1: datalake
A2: สำหรับบัญชี Bond | B2: Definition | C2: source system | D2: source table | E2: source column | F2: Formular | G2: Remark | H2: Mapping status
A3: Date | B3: as of date | H3: Not started
A4: account | B4: เลขที่บัญชี | H4: Not started
A5: custacct | B5: เลขที่ลูกค้า | H5: Not started
A6: xchgmkt | B6: เลขที่ตลาดซื้อขาย (3) | H6: Not started
A7: card id | B7: เลขประจำตัวผู้เสียภาษี | H7: Not started
A8: client_name | B8: ชื่อลูกค้า | H8: Not started
A9: team name | B9: ชื่อทีมที่ดูแลลูกค้า | H9: Not started
A10: mktname | B10: ชื่อ AO ที่ดูแลลูกค้า | H10: Not started
A11: flag บุคคลธรรมดา/นิติบุคคล | B11: บุคคลธรรมดา or นิติบุคคล | H11: Not started
A12: flag lombard loan | B12: Yes or No | H12: Not started
A13: flag property backed loan (PPBL) | B13: Yes or No | H13: Not started
A14: Open date | B14: วันที่เปิดบัญชี | H14: Not started
... A19: Max_asset_1Year | B19: นำมูลค่า Bond mktval ในแต่ละวัน มาหาค่าที่สูงสุดของแต่ละบัญชี | H19: Not started
A20: trade utilization% | B20: %utilization ของวงเงิน ที่คิดจากการนำ AR_trade/comp_creditline ของแต่ละวันย้อนหลัง 1 ปี มาหาค่าที่สูงสุด | F20: max of daily trade utilization daily trade utilization = AR_trade/comp_creditline | H20: Not started

Sheet sbl_report
C1: datalake
A2: สำหรับบัญชี SBL | B2: Definition | C2: source system | D2: source table | E2: source column | F2: Formular | G2: Remark | H2: Mapping status
A3: Date | B3: as of date | H3: Not started
A4: account | B4: เลขที่บัญชี | H4: Not started
A5: custacct | B5: เลขที่ลูกค้า | H5: Not started
A6: xchgmkt | B6: เลขที่ตลาดซื้อขาย (1) | H6: Not started
A7: card id | B7: เลขประจำตัวผู้เสียภาษี | H7: Not started
A8: client_name | B8: ชื่อลูกค้า | H8: Not started
A9: team name | B9: ชื่อทีมที่ดูแลลูกค้า | H9: Not started
A10: mktname | B10: ชื่อ AO ที่ดูแลลูกค้า | H10: Not started
A11: flag บุคคลธรรมดา/นิติบุคคล | B11: บุคคลธรรมดา or นิติบุคคล | H11: Not started
A12: flag lombard loan | B12: Yes or No | H12: Not started
A13: flag property backed loan (PPBL) | B13: Yes or No | H13: Not started
A14: flag TFSC | B14: Yes or No | H14: Not started
A15: flag algo trade | B15: Yes or No | H15: Not started
A16: flag cashcredit | H16: Not started
A17: open date | B17: วันที่เปิดบัญชี | H17: Not started
A18: Last trade | B18: วันที่มีการซื้อขายล่าสุด | H18: Not started
A19: Last date change credit line (วงเงินถาวร) | B19: วันที่ล่าสุดที่มีการปรับ วงเงินแบบถาวร | H19: Not started
A20: Credit line (วงเงินถาวร) | B20: ข้อมูลวงเงินแบบถาวร ของลูกค้า | H20: Not started
A21: Current asset | B21: มูลค่าหุ้นหลัง Haircut + เงินสด ของ as of date | H21: Not started
A22: Max_asset_1Year | B22: นำมูลค่าหุ้นหลัง Haircut + เงินสด ในแต่ละวัน มาหาค่าที่สูงสุดของแต่ละบัญชี | H22: Not started
A23: Loan (credit balance) | B23: มูลหนี้ของลูกค้า กรณีเป็นบัญชี Credit balance | H23: Not started
A24: trade utilization% | B24: %utilization ของวงเงิน ที่คิดจากการนำ AR_trade/comp_creditline ของแต่ละวันย้อนหลัง 1 ปี มาหาค่าที่สูงสุด | F24: max of daily trade utilization daily trade utilization = AR_trade/comp_creditline | H24: Not started
A25: loan utilization% | B25: %utilization ของวงเงิน ที่คิดจากการนำ debt/comp_creditline ของแต่ละวันย้อนหลัง 1 ปี มาหาค่าที่สูงสุด | F25: max of daily loan utilization daily loan utilization = AR_trade/comp_creditline | H25: Not started

Sheet offshore_report
C1: datalake
A2: สำหรับบัญชี Off-shore | B2: Definition | C2: source system | D2: source table | E2: source column | F2: Formular | G2: Remark | H2: Mapping status
A3: Date | B3: as of date | H3: Not started
A4: account | B4: เลขที่บัญชี | H4: Not started
A5: card id | B5: เลขประจำตัวผู้เสียภาษี | H5: Not started
A6: client_name | B6: ชื่อลูกค้า | H6: Not started
A7: team name | B7: ชื่อทีมที่ดูแลลูกค้า | H7: Not started
A8: mktname | B8: ชื่อ AO ที่ดูแลลูกค้า | H8: Not started
A9: flag บุคคลธรรมดา/นิติบุคคล | B9: บุคคลธรรมดา or นิติบุคคล | H9: Not started
A10: flag lombard loan | B10: Yes or No | H10: Not started
A11: flag property backed loan (PPBL) | B11: Yes or No | H11: Not started
A12: open date | B12: วันที่เปิดบัญชี | H12: Not started
A13: Last trade | B13: วันที่มีการซื้อขายล่าสุด | H13: Not started
A14: Last date change credit line (วงเงินถาวร) | B14: วันที่ล่าสุดที่มีการปรับ วงเงินแบบถาวร | H14: Not started
... A18: Max (มูลค่าซื้อ product ต่างๆ/credit line) since last year | B18: %utilization ของวงเงิน ที่คิดจากการนำ มูลค่าซื้อของทุก product / comp_creditline ของแต่ละวันมาหาค่าที่สูงสุด | H18: Not started

Sheet tfex_report
C1: datalake
A2: สำหรับบัญชี TFEX | B2: Definition | C2: source system | D2: source table | E2: source column | F2: Formular | G2: Remark | H2: Mapping status
A3: Date | B3: as of date | H3: Not started
A4: account | B4: เลขที่บัญชี | H4: Not started
A5: card id | B5: เลขประจำตัวผู้เสียภาษี | H5: Not started
A6: client_name | B6: ชื่อลูกค้า | H6: Not started
A7: team name | B7: ชื่อทีมที่ดูแลลูกค้า | H7: Not started
A8: mktname | B8: ชื่อ AO ที่ดูแลลูกค้า | H8: Not started
A9: flag บุคคลธรรมดา/นิติบุคคล | B9: บุคคลธรรมดา or นิติบุคคล | H9: Not started
A10: flag lombard loan | B10: Yes or No | H10: Not started
A11: flag property backed loan (PPBL) | B11: Yes or No | H11: Not started
A12: open date | B12: วันที่เปิดบัญชี | H12: Not started
A13: Last trade | B13: วันที่มีการซื้อขายล่าสุด | H13: Not started
A14: Last date change credit line (วงเงินถาวร) | B14: วันที่ล่าสุดที่มีการปรับ วงเงินแบบถาวร | H14: Not started
... A20: Max (initial margin/credit line) since last year | B20: %utilization ของวงเงิน ที่คิดจากการนำ initial margin/comp_creditline ของแต่ละวันมาหาค่าที่สูงสุด | H20: Not started

Sheet all_dropdown
B1: stock | C1: bond | D1: sbl | E1: offshore | F1: tfex | K1: Mapping status
A2: Total | B2: =COUNTA(equity_report!H3:H26) -> 24 | C2: =COUNTA(bond_report!H3:H20) -> 18 | D2: =COUNTA(sbl_report!H3:H25) -> 23 | E2: =COUNTA(offshore_report!H3:H18) -> 16 | F2: =COUNTA(tfex_report!H3:H20) -> 18 | K2: Done
A3: Done | B3: =COUNTIF(equity_report!$H$3:$H$26,$A3) -> 0 | C3: =COUNTIF(bond_report!$H$3:$H$20,$A3) -> 0 | D3: =COUNTIF(sbl_report!$H$3:$H$25,$A3) -> 0 | E3: =COUNTIF(offshore_report!$H$3:$H$18,$A3) -> 0 | F3: =COUNTIF(tfex_report!$H$3:$H$20,$A3) -> 0 | K3: Waiting for source to datalake
A4: Waiting for source to datalake | B4: =COUNTIF(equity_report!$H$3:$H$26,$A4) -> 0 | C4: =COUNTIF(bond_report!$H$3:$H$20,$A4) -> 0 | D4: =COUNTIF(sbl_report!$H$3:$H$25,$A4) -> 0 | E4: =COUNTIF(offshore_report!$H$3:$H$18,$A4) -> 0 | F4: =COUNTIF(tfex_report!$H$3:$H$20,$A4) -> 0 | K4: Finding fields
A5: Finding fields | B5: =COUNTIF(equity_report!$H$3:$H$26,$A5) -> 0 | C5: =COUNTIF(bond_report!$H$3:$H$20,$A5) -> 0 | D5: =COUNTIF(sbl_report!$H$3:$H$25,$A5) -> 0 | E5: =COUNTIF(offshore_report!$H$3:$H$18,$A5) -> 0 | F5: =COUNTIF(tfex_report!$H$3:$H$20,$A5) -> 0 | K5: Not started
A6: Not started | B6: =COUNTIF(equity_report!$H$3:$H$26,$A6) -> 24 | C6: =COUNTIF(bond_report!$H$3:$H$20,$A6) -> 18 | D6: =COUNTIF(sbl_report!$H$3:$H$25,$A6) -> 23 | E6: =COUNTIF(offshore_report!$H$3:$H$18,$A6) -> 16 | F6: =COUNTIF(tfex_report!$H$3:$H$20,$A6) -> 18
